main.py
my_mcp_weather_server_test-1.0.1.dist-info/METADATA
my_mcp_weather_server_test-1.0.1.dist-info/WHEEL
my_mcp_weather_server_test-1.0.1.dist-info/entry_points.txt
my_mcp_weather_server_test-1.0.1.dist-info/top_level.txt
my_mcp_weather_server_test-1.0.1.dist-info/RECORD
