Metadata-Version: 2.4
Name: my-mcp-weather-server-test
Version: 1.0.1
Summary: Add your description here
Requires-Python: >=3.10
Requires-Dist: httpx>=0.28.1
Requires-Dist: mcp>=1.8.0
